futurephysics/__init__.py
futurephysics/data.txt
futurephysics/story.py
futurephysics/wikipedia.py
futurephysics-0.8.dist-info/LICENCE
futurephysics-0.8.dist-info/METADATA
futurephysics-0.8.dist-info/WHEEL
futurephysics-0.8.dist-info/top_level.txt
futurephysics-0.8.dist-info/RECORD
