Metadata-Version: 2.1
Name: futurephysics
Version: 0.8
Summary: A package for generating stories about future concepts that are physically implementable.
Home-page: https://github.com/yachty66/futurephysics
Author: Max Hager
Author-email: maxhager28@gmail.com
License-File: LICENCE
Requires-Dist: openai ==0.28
Requires-Dist: marvin
Requires-Dist: requests
Requires-Dist: beautifulsoup4
Requires-Dist: google-cloud-storage
